main.py
ide_tools/__init__.py
ide_tools/router.py
ide_tools/common/__init__.py
ide_tools/common/hooks/__init__.py
ide_tools/common/hooks/init.py
ide_tools/common/hooks/output.py
ide_tools/common/hooks/prompt_submit.py
ide_tools/common/hooks/read_file.py
ide_tools/common/hooks/shell_execution.py
ide_tools/common/hooks/shell_parser_bashlex.py
ide_tools/common/hooks/types.py
ide_tools/common/hooks/utils.py
ide_tools/cursor/__init__.py
ide_tools/cursor/constants.py
ide_tools/cursor/format.py
ide_tools/cursor/router.py
mcpower_proxy-0.0.91.dist-info/licenses/LICENSE
modules/__init__.py
modules/apis/__init__.py
modules/apis/security_policy.py
modules/decision/__init__.py
modules/decision/decision_handler.py
modules/logs/__init__.py
modules/logs/audit_trail.py
modules/logs/logger.py
modules/redaction/__init__.py
modules/redaction/constants.py
modules/redaction/gitleaks_rules.py
modules/redaction/pii_rules.py
modules/redaction/redactor.py
modules/ui/__init__.py
modules/ui/classes.py
modules/ui/confirmation.py
modules/ui/simple_dialog.py
modules/ui/xdialog/__init__.py
modules/ui/xdialog/constants.py
modules/ui/xdialog/mac_dialogs.py
modules/ui/xdialog/tk_dialogs.py
modules/ui/xdialog/windows_custom_dialog.py
modules/ui/xdialog/windows_dialogs.py
modules/ui/xdialog/windows_structs.py
modules/ui/xdialog/yad_dialogs.py
modules/ui/xdialog/zenity_dialogs.py
modules/utils/__init__.py
modules/utils/cli.py
modules/utils/config.py
modules/utils/copy.py
modules/utils/ids.py
modules/utils/json.py
modules/utils/mcp_configs.py
modules/utils/platform.py
modules/utils/string.py
wrapper/__init__.py
wrapper/__version__.py
wrapper/middleware.py
wrapper/schema.py
wrapper/server.py
mcpower_proxy-0.0.91.dist-info/METADATA
mcpower_proxy-0.0.91.dist-info/WHEEL
mcpower_proxy-0.0.91.dist-info/entry_points.txt
mcpower_proxy-0.0.91.dist-info/top_level.txt
mcpower_proxy-0.0.91.dist-info/RECORD
