Metadata-Version: 2.4
Name: mcpower-proxy
Version: 0.0.91
Summary: MCPower Security proxy
Author-email: MCPower Security <support@mcpower.tech>
License:                                  Apache License
Keywords: mcp,security,proxy,monitoring,audit,redaction,policy-enforcement
Requires-Python: ~=3.11.0
License-File: LICENSE
Requires-Dist: fastmcp==2.13.0.2
Requires-Dist: httpx>=0.25.0
Requires-Dist: mcp>=1.0.0
Requires-Dist: watchdog>=3.0.0
Requires-Dist: jsonc-parser>=1.1.5
Requires-Dist: jsonpath-ng>=1.7.0
Requires-Dist: pydantic>=2.8.0
Requires-Dist: mcpower-shared==0.1.5
Requires-Dist: bashlex>=0.18
Dynamic: license-file
